{"id":361,"ayahs":[{"number":12,"arabic":"إِذَا رَأَتْهُم مِّن مَّكَانٍۭ بَعِيدٍۢ سَمِعُوا۟ لَهَا تَغَيُّظًۭا وَزَفِيرًۭا","translation":"when it shall face them from afar, they will hear its angry roar and its hiss;","audio":"https://cdn.islamic.network/quran/audio/128/ar.alafasy/2867.mp3","surahId":25,"words":[{"id":14253,"position":1,"arabic":"إِذَا","translation":"যখন (আগুন )","audioUrl":"wbw/025_012_001.mp3","charTypeName":"word"},{"id":14254,"position":2,"arabic":"رَأَتْهُم","translation":"তুমি দেখবে তাদেরকে","audioUrl":"wbw/025_012_002.mp3","charTypeName":"word"},{"id":14255,"position":3,"arabic":"مِّن","translation":"হ'তে","audioUrl":"wbw/025_012_003.mp3","charTypeName":"word"},{"id":14256,"position":4,"arabic":"مَّكَانٍۭ","translation":"জায়গা","audioUrl":"wbw/025_012_004.mp3","charTypeName":"word"},{"id":14257,"position":5,"arabic":"بَعِيدٍۢ","translation":"দূরবর্তী","audioUrl":"wbw/025_012_005.mp3","charTypeName":"word"},{"id":14258,"position":6,"arabic":"سَمِعُوا۟","translation":"তারা শুনতে পাবে (তখন)","audioUrl":"wbw/025_012_006.mp3","charTypeName":"word"},{"id":14259,"position":7,"arabic":"لَهَا","translation":"প্রতি তার","audioUrl":"wbw/025_012_007.mp3","charTypeName":"word"},{"id":14260,"position":8,"arabic":"تَغَيُّظًۭا","translation":"ক্রোধের গর্জন","audioUrl":"wbw/025_012_008.mp3","charTypeName":"word"},{"id":14261,"position":9,"arabic":"وَزَفِيرًۭا","translation":"ও চীৎকার","audioUrl":"wbw/025_012_009.mp3","charTypeName":"word"},{"id":14262,"position":10,"arabic":"١٢","translation":"(১২)","audioUrl":null,"charTypeName":"end"}]},{"number":13,"arabic":"وَإِذَآ أُلْقُوا۟ مِنْهَا مَكَانًۭا ضَيِّقًۭا مُّقَرَّنِينَ دَعَوْا۟ هُنَالِكَ ثُبُورًۭا","translation":"and when they are flung, linked [all] together, into a tight space within, they will pray for extinction there and then!","audio":"https://cdn.islamic.network/quran/audio/128/ar.alafasy/2868.mp3","surahId":25,"words":[{"id":15365,"position":1,"arabic":"وَإِذَآ","translation":"এবং যখন","audioUrl":"wbw/025_013_001.mp3","charTypeName":"word"},{"id":15366,"position":2,"arabic":"أُلْقُوا۟","translation":"নিক্ষেপ করা হবে","audioUrl":"wbw/025_013_002.mp3","charTypeName":"word"},{"id":15367,"position":3,"arabic":"مِنْهَا","translation":"তার মধ্যে","audioUrl":"wbw/025_013_003.mp3","charTypeName":"word"},{"id":15368,"position":4,"arabic":"مَكَانًۭا","translation":"জায়গায়","audioUrl":"wbw/025_013_004.mp3","charTypeName":"word"},{"id":15369,"position":5,"arabic":"ضَيِّقًۭا","translation":"সংকীর্ণ","audioUrl":"wbw/025_013_005.mp3","charTypeName":"word"},{"id":15370,"position":6,"arabic":"مُّقَرَّنِينَ","translation":"শিকল পরা অবস্থায়","audioUrl":"wbw/025_013_006.mp3","charTypeName":"word"},{"id":15371,"position":7,"arabic":"دَعَوْا۟","translation":"তারা ডাকবে","audioUrl":"wbw/025_013_007.mp3","charTypeName":"word"},{"id":15372,"position":8,"arabic":"هُنَالِكَ","translation":"সেখানে","audioUrl":"wbw/025_013_008.mp3","charTypeName":"word"},{"id":15373,"position":9,"arabic":"ثُبُورًۭا","translation":"মৃত্যুকে (ধ্বংস)","audioUrl":"wbw/025_013_009.mp3","charTypeName":"word"},{"id":15374,"position":10,"arabic":"١٣","translation":"(১৩)","audioUrl":null,"charTypeName":"end"}]},{"number":14,"arabic":"لَّا تَدْعُوا۟ ٱلْيَوْمَ ثُبُورًۭا وَٰحِدًۭا وَٱدْعُوا۟ ثُبُورًۭا كَثِيرًۭا","translation":"[But they will be told:] “Pray not today for one single extinction, but pray for many extinctions!”","audio":"https://cdn.islamic.network/quran/audio/128/ar.alafasy/2869.mp3","surahId":25,"words":[{"id":16423,"position":1,"arabic":"لَّا","translation":"\"(বলা হবে) না","audioUrl":"wbw/025_014_001.mp3","charTypeName":"word"},{"id":16424,"position":2,"arabic":"تَدْعُوا۟","translation":"তোমরা ডাকো","audioUrl":"wbw/025_014_002.mp3","charTypeName":"word"},{"id":16425,"position":3,"arabic":"ٱلْيَوْمَ","translation":"আজ","audioUrl":"wbw/025_014_003.mp3","charTypeName":"word"},{"id":16426,"position":4,"arabic":"ثُبُورًۭا","translation":"মৃত্যুকে (ধ্বংস)","audioUrl":"wbw/025_014_004.mp3","charTypeName":"word"},{"id":16427,"position":5,"arabic":"وَٰحِدًۭا","translation":"এক (বার)","audioUrl":"wbw/025_014_005.mp3","charTypeName":"word"},{"id":16428,"position":6,"arabic":"وَٱدْعُوا۟","translation":"বরং তোমরা ডাকো","audioUrl":"wbw/025_014_006.mp3","charTypeName":"word"},{"id":16429,"position":7,"arabic":"ثُبُورًۭا","translation":"মৃত্যু","audioUrl":"wbw/025_014_007.mp3","charTypeName":"word"},{"id":16430,"position":8,"arabic":"كَثِيرًۭا","translation":"বহুবার\"","audioUrl":"wbw/025_014_008.mp3","charTypeName":"word"},{"id":16431,"position":9,"arabic":"١٤","translation":"(১৪)","audioUrl":null,"charTypeName":"end"}]},{"number":15,"arabic":"قُلْ أَذَٰلِكَ خَيْرٌ أَمْ جَنَّةُ ٱلْخُلْدِ ٱلَّتِى وُعِدَ ٱلْمُتَّقُونَ ۚ كَانَتْ لَهُمْ جَزَآءًۭ وَمَصِيرًۭا","translation":"Say: “Which is better - that, or the paradise of life abiding which has been promised to the God-conscious as their reward and their journey’s end –","audio":"https://cdn.islamic.network/quran/audio/128/ar.alafasy/2870.mp3","surahId":25,"words":[{"id":17658,"position":1,"arabic":"قُلْ","translation":"বলো","audioUrl":"wbw/025_015_001.mp3","charTypeName":"word"},{"id":17659,"position":2,"arabic":"أَذَٰلِكَ","translation":"\"কি এটা","audioUrl":"wbw/025_015_002.mp3","charTypeName":"word"},{"id":17660,"position":3,"arabic":"خَيْرٌ","translation":"উত্তম","audioUrl":"wbw/025_015_003.mp3","charTypeName":"word"},{"id":17661,"position":4,"arabic":"أَمْ","translation":"না","audioUrl":"wbw/025_015_004.mp3","charTypeName":"word"},{"id":17662,"position":5,"arabic":"جَنَّةُ","translation":"জান্নাত","audioUrl":"wbw/025_015_005.mp3","charTypeName":"word"},{"id":17663,"position":6,"arabic":"ٱلْخُلْدِ","translation":"চিরস্থায়ী","audioUrl":"wbw/025_015_006.mp3","charTypeName":"word"},{"id":17664,"position":7,"arabic":"ٱلَّتِى","translation":"যা","audioUrl":"wbw/025_015_007.mp3","charTypeName":"word"},{"id":17665,"position":8,"arabic":"وُعِدَ","translation":"প্রতিশ্রুতি দেয়া হয়েছে","audioUrl":"wbw/025_015_008.mp3","charTypeName":"word"},{"id":17666,"position":9,"arabic":"ٱلْمُتَّقُونَ ۚ","translation":"মুত্তাকীদেরকে","audioUrl":"wbw/025_015_009.mp3","charTypeName":"word"},{"id":17668,"position":10,"arabic":"كَانَتْ","translation":"(সেটা) হবে","audioUrl":"wbw/025_015_011.mp3","charTypeName":"word"},{"id":17669,"position":11,"arabic":"لَهُمْ","translation":"জন্যে তাদের","audioUrl":"wbw/025_015_012.mp3","charTypeName":"word"},{"id":17670,"position":12,"arabic":"جَزَآءًۭ","translation":"পুরস্কার","audioUrl":"wbw/025_015_013.mp3","charTypeName":"word"},{"id":17671,"position":13,"arabic":"وَمَصِيرًۭا","translation":"ও প্রত্যাবর্তনস্থল","audioUrl":"wbw/025_015_014.mp3","charTypeName":"word"},{"id":17672,"position":14,"arabic":"١٥","translation":"(১৫)","audioUrl":null,"charTypeName":"end"}]},{"number":16,"arabic":"لَّهُمْ فِيهَا مَا يَشَآءُونَ خَٰلِدِينَ ۚ كَانَ عَلَىٰ رَبِّكَ وَعْدًۭا مَّسْـُٔولًۭا","translation":"a promise given by thy Sustainer, [always] to be prayed for?”","audio":"https://cdn.islamic.network/quran/audio/128/ar.alafasy/2871.mp3","surahId":25,"words":[{"id":18616,"position":1,"arabic":"لَّهُمْ","translation":"জন্যে তাদের (থাকবে)","audioUrl":"wbw/025_016_001.mp3","charTypeName":"word"},{"id":18617,"position":2,"arabic":"فِيهَا","translation":"তার মধ্যে","audioUrl":"wbw/025_016_002.mp3","charTypeName":"word"},{"id":18618,"position":3,"arabic":"مَا","translation":"যা","audioUrl":"wbw/025_016_003.mp3","charTypeName":"word"},{"id":18619,"position":4,"arabic":"يَشَآءُونَ","translation":"তারা চাইবে","audioUrl":"wbw/025_016_004.mp3","charTypeName":"word"},{"id":18620,"position":5,"arabic":"خَـٰلِدِينَ ۚ","translation":"তারা স্থায়ী হবে (সেখানে)","audioUrl":"wbw/025_016_005.mp3","charTypeName":"word"},{"id":18622,"position":6,"arabic":"كَانَ","translation":"(এটা) হলো","audioUrl":"wbw/025_016_007.mp3","charTypeName":"word"},{"id":18623,"position":7,"arabic":"عَلَىٰ","translation":"উপর","audioUrl":"wbw/025_016_008.mp3","charTypeName":"word"},{"id":18624,"position":8,"arabic":"رَبِّكَ","translation":"তোমার রবের","audioUrl":"wbw/025_016_009.mp3","charTypeName":"word"},{"id":18625,"position":9,"arabic":"وَعْدًۭا","translation":"প্রতিশ্রুতি","audioUrl":"wbw/025_016_010.mp3","charTypeName":"word"},{"id":18626,"position":10,"arabic":"مَّسْـُٔولًۭا","translation":"অবশ্য পালনীয়\"","audioUrl":"wbw/025_016_011.mp3","charTypeName":"word"},{"id":18627,"position":11,"arabic":"١٦","translation":"(১৬)","audioUrl":null,"charTypeName":"end"}]},{"number":17,"arabic":"وَيَوْمَ يَحْشُرُهُمْ وَمَا يَعْبُدُونَ مِن دُونِ ٱللَّهِ فَيَقُولُ ءَأَنتُمْ أَضْلَلْتُمْ عِبَادِى هَٰٓؤُلَآءِ أَمْ هُمْ ضَلُّوا۟ ٱلسَّبِيلَ","translation":"BUT [as for people who are oblivious of thy Sus­tainer’s oneness -] one Day He will gather them together with all that they [now] worship instead of God, and will ask [those to whom divinity was falsely ascribed]: “Was it you who led these My creatures astray, or did they by themselves stray from the right path?”","audio":"https://cdn.islamic.network/quran/audio/128/ar.alafasy/2872.mp3","surahId":25,"words":[{"id":19664,"position":1,"arabic":"وَيَوْمَ","translation":"আর যেদিন","audioUrl":"wbw/025_017_001.mp3","charTypeName":"word"},{"id":19665,"position":2,"arabic":"يَحْشُرُهُمْ","translation":"তিনি একত্র করবেন তাদেরকে","audioUrl":"wbw/025_017_002.mp3","charTypeName":"word"},{"id":19666,"position":3,"arabic":"وَمَا","translation":"এবং যাদেরকে","audioUrl":"wbw/025_017_003.mp3","charTypeName":"word"},{"id":19667,"position":4,"arabic":"يَعْبُدُونَ","translation":"তারা ইবাদাত করতো","audioUrl":"wbw/025_017_004.mp3","charTypeName":"word"},{"id":19668,"position":5,"arabic":"مِن","translation":"থেকে","audioUrl":"wbw/025_017_005.mp3","charTypeName":"word"},{"id":19669,"position":6,"arabic":"دُونِ","translation":"পরিবর্তে","audioUrl":"wbw/025_017_006.mp3","charTypeName":"word"},{"id":19670,"position":7,"arabic":"ٱللَّهِ","translation":"আল্লাহর","audioUrl":"wbw/025_017_007.mp3","charTypeName":"word"},{"id":19671,"position":8,"arabic":"فَيَقُولُ","translation":"তখন তিনি বলবেন","audioUrl":"wbw/025_017_008.mp3","charTypeName":"word"},{"id":19672,"position":9,"arabic":"ءَأَنتُمْ","translation":"\"কি তোমরাই","audioUrl":"wbw/025_017_009.mp3","charTypeName":"word"},{"id":19673,"position":10,"arabic":"أَضْلَلْتُمْ","translation":"তোমরা বিভ্রান্ত করেছিলে","audioUrl":"wbw/025_017_010.mp3","charTypeName":"word"},{"id":19674,"position":11,"arabic":"عِبَادِى","translation":"আমার দাসদেরকে","audioUrl":"wbw/025_017_011.mp3","charTypeName":"word"},{"id":19675,"position":12,"arabic":"هَـٰٓؤُلَآءِ","translation":"এসব","audioUrl":"wbw/025_017_012.mp3","charTypeName":"word"},{"id":19676,"position":13,"arabic":"أَمْ","translation":"না","audioUrl":"wbw/025_017_013.mp3","charTypeName":"word"},{"id":19677,"position":14,"arabic":"هُمْ","translation":"তারাই","audioUrl":"wbw/025_017_014.mp3","charTypeName":"word"},{"id":19678,"position":15,"arabic":"ضَلُّوا۟","translation":"ভ্রান্ত হয়েছিলো","audioUrl":"wbw/025_017_015.mp3","charTypeName":"word"},{"id":19679,"position":16,"arabic":"ٱلسَّبِيلَ","translation":"পথ\"","audioUrl":"wbw/025_017_016.mp3","charTypeName":"word"},{"id":19680,"position":17,"arabic":"١٧","translation":"(১৭)","audioUrl":null,"charTypeName":"end"}]},{"number":18,"arabic":"قَالُوا۟ سُبْحَٰنَكَ مَا كَانَ يَنۢبَغِى لَنَآ أَن نَّتَّخِذَ مِن دُونِكَ مِنْ أَوْلِيَآءَ وَلَٰكِن مَّتَّعْتَهُمْ وَءَابَآءَهُمْ حَتَّىٰ نَسُوا۟ ٱلذِّكْرَ وَكَانُوا۟ قَوْمًۢا بُورًۭا","translation":"They will answer: “Limitless art Thou in Thy glory! It was inconceivable for us to take for our masters anyone but Thyself! But [as for them -] Thou didst allow them and their forefathers to enjoy [the pleasures of] life to such an extent that they forgot all remembrance [of Thee]: for they were people devoid of all good.”","audio":"https://cdn.islamic.network/quran/audio/128/ar.alafasy/2873.mp3","surahId":25,"words":[{"id":20757,"position":1,"arabic":"قَالُوا۟","translation":"তারা বলবে","audioUrl":"wbw/025_018_001.mp3","charTypeName":"word"},{"id":20758,"position":2,"arabic":"سُبْحَـٰنَكَ","translation":"\"সত্ত্বা আপনার পবিত্র মহান","audioUrl":"wbw/025_018_002.mp3","charTypeName":"word"},{"id":20759,"position":3,"arabic":"مَا","translation":"না","audioUrl":"wbw/025_018_003.mp3","charTypeName":"word"},{"id":20760,"position":4,"arabic":"كَانَ","translation":"ছিলো","audioUrl":"wbw/025_018_004.mp3","charTypeName":"word"},{"id":20761,"position":5,"arabic":"يَنۢبَغِى","translation":"উচিত","audioUrl":"wbw/025_018_005.mp3","charTypeName":"word"},{"id":20762,"position":6,"arabic":"لَنَآ","translation":"জন্যে আমাদের","audioUrl":"wbw/025_018_006.mp3","charTypeName":"word"},{"id":20763,"position":7,"arabic":"أَن","translation":"যে","audioUrl":"wbw/025_018_007.mp3","charTypeName":"word"},{"id":20764,"position":8,"arabic":"نَّتَّخِذَ","translation":"গ্রহণ করবো আমরা","audioUrl":"wbw/025_018_008.mp3","charTypeName":"word"},{"id":20765,"position":9,"arabic":"مِن","translation":"থেকে","audioUrl":"wbw/025_018_009.mp3","charTypeName":"word"},{"id":20766,"position":10,"arabic":"دُونِكَ","translation":"আপনার পরিবর্তে","audioUrl":"wbw/025_018_010.mp3","charTypeName":"word"},{"id":20767,"position":11,"arabic":"مِنْ","translation":"কোন","audioUrl":"wbw/025_018_011.mp3","charTypeName":"word"},{"id":20768,"position":12,"arabic":"أَوْلِيَآءَ","translation":"অভিভাবক","audioUrl":"wbw/025_018_012.mp3","charTypeName":"word"},{"id":20769,"position":13,"arabic":"وَلَـٰكِن","translation":"কিন্তু","audioUrl":"wbw/025_018_013.mp3","charTypeName":"word"},{"id":20770,"position":14,"arabic":"مَّتَّعْتَهُمْ","translation":"আপনি ভোগ-সম্ভার দিয়েছেলেন তাদেরকে","audioUrl":"wbw/025_018_014.mp3","charTypeName":"word"},{"id":20771,"position":15,"arabic":"وَءَابَآءَهُمْ","translation":"এবং তাদের পিতৃ পুরুষদেরকেও","audioUrl":"wbw/025_018_015.mp3","charTypeName":"word"},{"id":20772,"position":16,"arabic":"حَتَّىٰ","translation":"শেষ পর্যন্ত","audioUrl":"wbw/025_018_016.mp3","charTypeName":"word"},{"id":20773,"position":17,"arabic":"نَسُوا۟","translation":"তারা ভুলে গিয়েছিলো","audioUrl":"wbw/025_018_017.mp3","charTypeName":"word"},{"id":20774,"position":18,"arabic":"ٱلذِّكْرَ","translation":"(আপনার) স্মরণ","audioUrl":"wbw/025_018_018.mp3","charTypeName":"word"},{"id":20775,"position":19,"arabic":"وَكَانُوا۟","translation":"এবং তারা হয়েছিলো","audioUrl":"wbw/025_018_019.mp3","charTypeName":"word"},{"id":20776,"position":20,"arabic":"قَوْمًۢا","translation":"জাতিতে","audioUrl":"wbw/025_018_020.mp3","charTypeName":"word"},{"id":20777,"position":21,"arabic":"بُورًۭا","translation":"ধ্বংসপ্রাপ্ত\"","audioUrl":"wbw/025_018_021.mp3","charTypeName":"word"},{"id":20778,"position":22,"arabic":"١٨","translation":"(১৮)","audioUrl":null,"charTypeName":"end"}]},{"number":19,"arabic":"فَقَدْ كَذَّبُوكُم بِمَا تَقُولُونَ فَمَا تَسْتَطِيعُونَ صَرْفًۭا وَلَا نَصْرًۭا ۚ وَمَن يَظْلِم مِّنكُمْ نُذِقْهُ عَذَابًۭا كَبِيرًۭا","translation":"[Thereupon God will say:] “And now, they [whom you regarded as divine] have given the lie to all your [past] assertions, and you can neither ward off [your punishment] nor obtain any succour! For, whoever of you has committed [such] evil, him shall We cause to taste great suffering!”","audio":"https://cdn.islamic.network/quran/audio/128/ar.alafasy/2874.mp3","surahId":25,"words":[{"id":21897,"position":1,"arabic":"فَقَدْ","translation":"\"তখন নিশ্চয়ই","audioUrl":"wbw/025_019_001.mp3","charTypeName":"word"},{"id":21898,"position":2,"arabic":"كَذَّبُوكُم","translation":"তারা মিথ্যা সাব্যস্ত করেছে তোমাদেরকে","audioUrl":"wbw/025_019_002.mp3","charTypeName":"word"},{"id":21899,"position":3,"arabic":"بِمَا","translation":"ঐবিষয় যা","audioUrl":"wbw/025_019_003.mp3","charTypeName":"word"},{"id":21900,"position":4,"arabic":"تَقُولُونَ","translation":"তোমরা বলছো","audioUrl":"wbw/025_019_004.mp3","charTypeName":"word"},{"id":21901,"position":5,"arabic":"فَمَا","translation":"সুতরাং না","audioUrl":"wbw/025_019_005.mp3","charTypeName":"word"},{"id":21902,"position":6,"arabic":"تَسْتَطِيعُونَ","translation":"তোমরা পারবে","audioUrl":"wbw/025_019_006.mp3","charTypeName":"word"},{"id":21903,"position":7,"arabic":"صَرْفًۭا","translation":"ফিরাতে (শাস্তি)","audioUrl":"wbw/025_019_007.mp3","charTypeName":"word"},{"id":21904,"position":8,"arabic":"وَلَا","translation":"আর না","audioUrl":"wbw/025_019_008.mp3","charTypeName":"word"},{"id":21905,"position":9,"arabic":"نَصْرًۭا ۚ","translation":"সাহায্যও (পাবে)\"","audioUrl":"wbw/025_019_009.mp3","charTypeName":"word"},{"id":21907,"position":10,"arabic":"وَمَن","translation":"আর যে","audioUrl":"wbw/025_019_011.mp3","charTypeName":"word"},{"id":21908,"position":11,"arabic":"يَظْلِم","translation":"সীমালঙ্ঘন করবে","audioUrl":"wbw/025_019_012.mp3","charTypeName":"word"},{"id":21909,"position":12,"arabic":"مِّنكُمْ","translation":"তোমাদের মধ্য হ'তে","audioUrl":"wbw/025_019_013.mp3","charTypeName":"word"},{"id":21910,"position":13,"arabic":"نُذِقْهُ","translation":"তাকে আস্বাদ করাবো আমরা","audioUrl":"wbw/025_019_014.mp3","charTypeName":"word"},{"id":21911,"position":14,"arabic":"عَذَابًۭا","translation":"শাস্তি","audioUrl":"wbw/025_019_015.mp3","charTypeName":"word"},{"id":21912,"position":15,"arabic":"كَبِيرًۭا","translation":"গুরুতর","audioUrl":"wbw/025_019_016.mp3","charTypeName":"word"},{"id":21913,"position":16,"arabic":"١٩","translation":"(১৯)","audioUrl":null,"charTypeName":"end"}]},{"number":20,"arabic":"وَمَآ أَرْسَلْنَا قَبْلَكَ مِنَ ٱلْمُرْسَلِينَ إِلَّآ إِنَّهُمْ لَيَأْكُلُونَ ٱلطَّعَامَ وَيَمْشُونَ فِى ٱلْأَسْوَاقِ ۗ وَجَعَلْنَا بَعْضَكُمْ لِبَعْضٍۢ فِتْنَةً أَتَصْبِرُونَ ۗ وَكَانَ رَبُّكَ بَصِيرًۭا","translation":"AND [even] before thee, [O Muhammad,] We never sent as Our message-bearers any but [mortal men] who indeed ate food [like other human beings] and went about in the market places: for [it is thus that] We cause you [human beings] to be a means of testing one another. Are you able to endure [this test] with patience? For [remember, O man,] thy Sustainer is truly all-seeing!","audio":"https://cdn.islamic.network/quran/audio/128/ar.alafasy/2875.mp3","surahId":25,"words":[{"id":22941,"position":1,"arabic":"وَمَآ","translation":"আর (হে নাবী) না","audioUrl":"wbw/025_020_001.mp3","charTypeName":"word"},{"id":22942,"position":2,"arabic":"أَرْسَلْنَا","translation":"আমরা পাঠিয়েছি","audioUrl":"wbw/025_020_002.mp3","charTypeName":"word"},{"id":22943,"position":3,"arabic":"قَبْلَكَ","translation":"তোমার পূর্বে (কাউকে)","audioUrl":"wbw/025_020_003.mp3","charTypeName":"word"},{"id":22944,"position":4,"arabic":"مِنَ","translation":"মধ্য হ'তে","audioUrl":"wbw/025_020_004.mp3","charTypeName":"word"},{"id":22945,"position":5,"arabic":"ٱلْمُرْسَلِينَ","translation":"রাসূলদের","audioUrl":"wbw/025_020_005.mp3","charTypeName":"word"},{"id":22946,"position":6,"arabic":"إِلَّآ","translation":"এ ছাড়া যে","audioUrl":"wbw/025_020_006.mp3","charTypeName":"word"},{"id":22947,"position":7,"arabic":"إِنَّهُمْ","translation":"নিশ্চয়ই তারা","audioUrl":"wbw/025_020_007.mp3","charTypeName":"word"},{"id":22948,"position":8,"arabic":"لَيَأْكُلُونَ","translation":"অবশ্যই তারা খায়","audioUrl":"wbw/025_020_008.mp3","charTypeName":"word"},{"id":22949,"position":9,"arabic":"ٱلطَّعَامَ","translation":"খাবার","audioUrl":"wbw/025_020_009.mp3","charTypeName":"word"},{"id":22950,"position":10,"arabic":"وَيَمْشُونَ","translation":"ও চলাফেরা করে","audioUrl":"wbw/025_020_010.mp3","charTypeName":"word"},{"id":22951,"position":11,"arabic":"فِى","translation":"মধ্যে","audioUrl":"wbw/025_020_011.mp3","charTypeName":"word"},{"id":22952,"position":12,"arabic":"ٱلْأَسْوَاقِ ۗ","translation":"হাট-বাজারগুলোর","audioUrl":"wbw/025_020_012.mp3","charTypeName":"word"},{"id":22954,"position":13,"arabic":"وَجَعَلْنَا","translation":"আর আমরা করেছি","audioUrl":"wbw/025_020_014.mp3","charTypeName":"word"},{"id":22955,"position":14,"arabic":"بَعْضَكُمْ","translation":"একে তোমাদের","audioUrl":"wbw/025_020_015.mp3","charTypeName":"word"},{"id":22956,"position":15,"arabic":"لِبَعْضٍۢ","translation":"জন্যে অপরের","audioUrl":"wbw/025_020_016.mp3","charTypeName":"word"},{"id":22957,"position":16,"arabic":"فِتْنَةً","translation":"পরীক্ষাস্বরূপ","audioUrl":"wbw/025_020_017.mp3","charTypeName":"word"},{"id":22958,"position":17,"arabic":"أَتَصْبِرُونَ ۗ","translation":"তোমরা ধৈর্য ধারণ করবে কি","audioUrl":"wbw/025_020_018.mp3","charTypeName":"word"},{"id":22960,"position":18,"arabic":"وَكَانَ","translation":"আর (জেনে রেখো) হলেন","audioUrl":"wbw/025_020_020.mp3","charTypeName":"word"},{"id":22961,"position":19,"arabic":"رَبُّكَ","translation":"তোমার রব (এমন যে)","audioUrl":"wbw/025_020_021.mp3","charTypeName":"word"},{"id":22962,"position":20,"arabic":"بَصِيرًۭا","translation":"তিনি সবকিছু দেখেন","audioUrl":"wbw/025_020_022.mp3","charTypeName":"word"},{"id":22963,"position":21,"arabic":"٢٠","translation":"(২০)","audioUrl":null,"charTypeName":"end"}]}]}